README.md
pyproject.toml
setup.cfg
dsptool/__init__.py
dsptool/circular_buffer.py
dsptool/scale.py
dsptool/window.py
dsptool.egg-info/PKG-INFO
dsptool.egg-info/SOURCES.txt
dsptool.egg-info/dependency_links.txt
dsptool.egg-info/requires.txt
dsptool.egg-info/top_level.txt