Metadata-Version: 2.1
Name: dsptool
Version: 0.5.1
Summary: A set of tools for DSP projects
Home-page: https://github.com/tandav/dsptool
Author: Alexander Rodionov
Author-email: tandav@tandav.me
Requires-Python: >=3.8
